Metadata-Version: 2.1
Name: happiestfuntokenizing
Version: 0.0.7
Summary: This code is updated by author to adapt to Python3. The former version of code implements a basic, Twitter-aware tokenizer. Originally developed by Christopher Potts and updated by the World Well-Being Project based out of the University of Pennsylvania and Stony Brook University. Shared with permission.
Home-page: http://dlatk.wwbp.org
Author: Christopher Potts, H. Andrew Schwartz, Maarten Sap, Salvatore Giorgi, Caspar Chan
Author-email: hansens@sas.upenn.edu, sgiorgi@sas.upenn.edu
License: GNU General Public License v3 (GPLv3)
Download-URL: https://github.com/channel960608/happiestfuntokenizing
Platform: UNKNOWN
Classifier: Environment :: Console
Classifier: Natural Language :: English
Classifier: Intended Audience :: End Users/Desktop
Classifier: Intended Audience :: Developers
Classifier: Intended Audience :: Science/Research
Classifier: Programming Language :: Python
Classifier: Programming Language :: Python :: 3
Classifier: Programming Language :: Python :: 3.6
Classifier: Topic :: Scientific/Engineering
